{"pid":100589193,"p":0,"uid":12018749,"title":"星川サラ","author":"兎こ","r18":true,"width":1984,"height":3508,"tags":["R-18","星川サラ","Sara Hoshikawa","にじさんじ","彩虹社","巨乳","large breasts","おっぱい","欧派","揉みしだきたい乳","诱人把玩的乳房","バーチャルYouTuber","虚拟主播","お腹","腹部","オッドアイ","异色瞳"],"ext":"jpg","aiType":0,"uploadDate":1660836527000,"urls":{"regular":"https:\/\/i.pixiv.re\/img-master\/img\/2022\/08\/19\/00\/28\/47\/100589193_p0_master1200.jpg"},"url":"\/img-master\/img\/2022\/08\/19\/00\/28\/47\/100589193_p0_master1200.jpg"}