{"pid":101323713,"p":0,"uid":871625,"title":"ブレストちゃん","author":"lambda","r18":true,"width":738,"height":900,"tags":["R-18","アズールレーン","碧蓝航线","ブレスト(アズールレーン)","布雷斯特（碧蓝航线）","おっぱい","欧派","胸ポチ","凸点","エルフ耳","精灵耳","四つん這い","on all fours","極上の乳","极上乳房","揉みしだきたい乳","诱人把玩的乳房"],"ext":"jpg","aiType":0,"uploadDate":1663513214000,"urls":{"regular":"https:\/\/i.pixiv.re\/img-master\/img\/2022\/09\/19\/00\/00\/14\/101323713_p0_master1200.jpg"},"url":"\/img-master\/img\/2022\/09\/19\/00\/00\/14\/101323713_p0_master1200.jpg"}