{"pid":101900994,"p":3,"uid":17065499,"title":"skebでご依頼いただいた絵+α","author":"ダイン=ガロン","r18":true,"width":1039,"height":1228,"tags":["R-18","skeb","FEH","戦国プロヴィデンス","よそのこ","someone else's OC","オリジナル","原创","シリアス(アズールレーン)","天狼星（碧蓝航线）","ファイアーエムブレム","圣火降魔录","カゲロウ(FEif)","Kagero (FE Fates)","すっぽんぽん","buck naked"],"ext":"png","aiType":0,"uploadDate":1665650158000,"urls":{"regular":"https:\/\/i.pixiv.re\/img-master\/img\/2022\/10\/13\/17\/35\/58\/101900994_p3_master1200.jpg"},"url":"\/img-master\/img\/2022\/10\/13\/17\/35\/58\/101900994_p3_master1200.jpg"}