{"pid":102078313,"p":0,"uid":14687979,"title":"异刃3委托","author":"十七云紫","r18":true,"width":3415,"height":2580,"tags":["R-18","Xenoblade","Xenoblade3","拘束","束缚","露出","暴露","魅惑のふともも","魅惑的大腿","ユーニ(ゼノブレイド3)","Eunie (Xenoblable Chronicles 3)","ゼノブレイド3","异度神剑3","ミオ(ゼノブレイド3)","Mio (Xenoblade 3)"],"ext":"jpg","aiType":0,"uploadDate":1666204992000,"urls":{"regular":"https:\/\/i.pixiv.re\/img-master\/img\/2022\/10\/20\/03\/43\/12\/102078313_p0_master1200.jpg"},"url":"\/img-master\/img\/2022\/10\/20\/03\/43\/12\/102078313_p0_master1200.jpg"}