{"pid":102135348,"p":0,"uid":44906939,"title":"イラストリアスさん","author":"むむむ星人","r18":true,"width":2079,"height":2918,"tags":["R-18","拘束","束缚","猿轡","猿辔","イラストリアス(アズールレーン)","光辉(碧蓝航线)","アズールレーン","碧蓝航线","首枷","pillory","開口マスク","open mouth gag","裸","nude","ギロチン拘束"],"ext":"png","aiType":0,"uploadDate":1666415149000,"urls":{"regular":"https:\/\/i.pixiv.re\/img-master\/img\/2022\/10\/22\/14\/05\/49\/102135348_p0_master1200.jpg"},"url":"\/img-master\/img\/2022\/10\/22\/14\/05\/49\/102135348_p0_master1200.jpg"}