{"pid":102752126,"p":0,"uid":10891,"title":"女神のお花","author":"ホルモン恋次郎","r18":true,"width":811,"height":1200,"tags":["R-18","この素晴らしい世界に祝福を!","为美好的世界献上祝福！","アクア(このすば)","阿库娅（为美好的世界献上祝福）","マイクロビキニ","极小比基尼","アナル","肛门","舐め回したい穴","想舔到不行的穴","マニキュア","美甲","アナルの造詣が深い","深得肛门真谛","尻神様","尻神样"],"ext":"png","aiType":1,"uploadDate":1668310014000,"urls":{"regular":"https:\/\/i.pixiv.re\/img-master\/img\/2022\/11\/13\/12\/26\/54\/102752126_p0_master1200.jpg"},"url":"\/img-master\/img\/2022\/11\/13\/12\/26\/54\/102752126_p0_master1200.jpg"}