{"pid":102895335,"p":0,"uid":6048589,"title":"大人気の後藤ひとり","author":"鶸虫wolm","r18":true,"width":946,"height":1595,"tags":["R-18","後藤ひとり","ぼっち・ざ・ろっく!","ぼっちちゃん","小波奇","山田リョウ","山田凉","ひとりハーレム","Bocchi Harem","生まれたままの姿(産まれたままの姿)全裸(ヌード)","birthday suit","乳吸い","吸吮乳房","百合","yuri"],"ext":"jpg","aiType":1,"uploadDate":1668770009000,"urls":{"regular":"https:\/\/i.pixiv.re\/img-master\/img\/2022\/11\/18\/20\/13\/29\/102895335_p0_master1200.jpg"},"url":"\/img-master\/img\/2022\/11\/18\/20\/13\/29\/102895335_p0_master1200.jpg"}