{"pid":103414605,"p":0,"uid":85489721,"title":"マリー","author":"春希ミカン","r18":true,"width":3600,"height":5100,"tags":["R-18","伊落マリー(体操服)","伊落玛丽（体操服）","ブルーアーカイブ","碧蓝档案","伊落マリー","Mari Iochi","けもみみ","兽耳","体操服","gym uniform","M字開脚","M字开腿","体育着","事後","事后","更衣室","changing room"],"ext":"jpg","aiType":1,"uploadDate":1670403601000,"urls":{"regular":"https:\/\/i.pixiv.re\/img-master\/img\/2022\/12\/07\/18\/00\/01\/103414605_p0_master1200.jpg"},"url":"\/img-master\/img\/2022\/12\/07\/18\/00\/01\/103414605_p0_master1200.jpg"}