{"pid":103504017,"p":4,"uid":3316400,"title":"マイクロビキニ部美遊","author":"MだSたろう","r18":true,"width":1771,"height":2508,"tags":["R-18","Fate\/GrandOrder","FGO","プリズマ☆イリヤ","魔法少女☆伊莉雅","美遊・エーデルフェルト","美游·艾德费尔特","イリヤスフィール・フォン・アインツベルン","伊莉雅丝菲尔・冯・爱因兹贝伦","マイクロビキニ","极小比基尼","輪姦","轮姦"],"ext":"jpg","aiType":1,"uploadDate":1670685477000,"urls":{"regular":"https:\/\/i.pixiv.re\/img-master\/img\/2022\/12\/11\/00\/17\/57\/103504017_p4_master1200.jpg"},"url":"\/img-master\/img\/2022\/12\/11\/00\/17\/57\/103504017_p4_master1200.jpg"}