{"pid":103508566,"p":1,"uid":54573972,"title":"【来点兔子吗】バンドルゲーム！","author":"bin lu","r18":true,"width":1024,"height":1536,"tags":["R-18","请问您今天要来点兔子吗?","loli","チノちゃん","智乃酱","香風智乃","香风智乃","ごちうさ","点兔","ご注文はうさぎですか?","请问您今天要来点兔子吗？","全裸","completely naked","拘束","束缚","催眠","Hypnosis"],"ext":"png","aiType":1,"uploadDate":1670697200000,"urls":{"regular":"https:\/\/i.pixiv.re\/img-master\/img\/2022\/12\/11\/03\/33\/20\/103508566_p1_master1200.jpg"},"url":"\/img-master\/img\/2022\/12\/11\/03\/33\/20\/103508566_p1_master1200.jpg"}