{"pid":104107753,"p":1,"uid":1428649,"title":"・・・?（R18差分有）","author":"肉　FANBOX♥fantia","r18":true,"width":2049,"height":3252,"tags":["R-18","沙花叉クロヱ","沙花叉库洛艾","バーチャルYouTuber","虚拟主播","揉みしだきたい乳","诱人把玩的乳房","ホロライブ","Hololive","谷間","cleavage","VTuber","virtual YouTuber","巨乳","large breasts","hololive"],"ext":"jpg","aiType":1,"uploadDate":1672503237000,"urls":{"regular":"https:\/\/i.pixiv.re\/img-master\/img\/2023\/01\/01\/01\/13\/57\/104107753_p1_master1200.jpg"},"url":"\/img-master\/img\/2023\/01\/01\/01\/13\/57\/104107753_p1_master1200.jpg"}