{"pid":104286185,"p":0,"uid":3026471,"title":"クソザコ魔法少女ちゃん③","author":"だぶき","r18":true,"width":992,"height":1403,"tags":["R-18","魔法少女","magical girl","触手","tentacle","拘束","束缚","異種姦","异种姦","ピンク髪","粉色头发","敗北","败北","凌辱","sexual assault","キメセク","嗑药啪","首絞め","掐脖子"],"ext":"jpg","aiType":1,"uploadDate":1672994947000,"urls":{"regular":"https:\/\/i.pixiv.re\/img-master\/img\/2023\/01\/06\/17\/49\/07\/104286185_p0_master1200.jpg"},"url":"\/img-master\/img\/2023\/01\/06\/17\/49\/07\/104286185_p0_master1200.jpg"}