{"pid":104359923,"p":0,"uid":3415009,"title":"sister （and futa.ver）","author":"STmast","r18":true,"width":3472,"height":2456,"tags":["R-18","ふたなり","扶他","エロ衣装","H服装","loli","萝莉","母乳","breast milk","巨乳","large breasts","贫乳","flat chest","射精","ejaculation","戦車擬人化","Tank Anthropomorphization","尻神様","尻神样"],"ext":"jpg","aiType":1,"uploadDate":1673190588000,"urls":{"regular":"https:\/\/i.pixiv.re\/img-master\/img\/2023\/01\/09\/00\/09\/48\/104359923_p0_master1200.jpg"},"url":"\/img-master\/img\/2023\/01\/09\/00\/09\/48\/104359923_p0_master1200.jpg"}