{"pid":104544038,"p":0,"uid":29535589,"title":"猫塚响败北调教\/Hibiki lose!","author":"Archive","r18":true,"width":1789,"height":2400,"tags":["R-18","猫塚ヒビキ","Nekozuka Hibiki","ブルーアーカイブ","碧蓝档案","中出し","中出","エロ衣装","H服装","身体に落書き","身体涂鸦","失神","fainting","長手袋","长手套","口枷","mouth gag","潮吹き","潮吹"],"ext":"jpg","aiType":1,"uploadDate":1673781127000,"urls":{"regular":"https:\/\/i.pixiv.re\/img-master\/img\/2023\/01\/15\/20\/12\/07\/104544038_p0_master1200.jpg"},"url":"\/img-master\/img\/2023\/01\/15\/20\/12\/07\/104544038_p0_master1200.jpg"}