{"pid":106524280,"p":1,"uid":3193378,"title":"キサキ","author":"電磁砲二期","r18":true,"width":1064,"height":1500,"tags":["R-18","キサキ","妃咲","キサキ(ブルーアーカイブ)","妃咲（蔚蓝档案）","チャイナ服","中国服装","ぱんつ","胖次","ハイヒール","高跟鞋","揉みしだきたい乳","诱人把玩的乳房","ブルーアーカイブ","碧蓝档案","竜華キサキ","龙华妃咲","アナルチラ","肛门走光"],"ext":"jpg","aiType":1,"uploadDate":1679670057000,"urls":{"regular":"https:\/\/i.pixiv.re\/img-master\/img\/2023\/03\/25\/00\/00\/57\/106524280_p1_master1200.jpg"},"url":"\/img-master\/img\/2023\/03\/25\/00\/00\/57\/106524280_p1_master1200.jpg"}