{"pid":107124000,"p":0,"uid":35688828,"title":"珊瑚宫心海 Kokomi NSFW","author":"bright sky","r18":true,"width":1478,"height":3072,"tags":["R-18","珊瑚宫心海","Sangonomiya Kokomi","Kokomi","Genshin","GenshinImpact","女の子","女孩子","極上の乳","极上乳房","原神","Genshin Impact","すじ","骆驼趾"],"ext":"jpg","aiType":2,"uploadDate":1681316775000,"urls":{"regular":"https:\/\/i.pixiv.re\/img-master\/img\/2023\/04\/13\/01\/26\/15\/107124000_p0_master1200.jpg"},"url":"\/img-master\/img\/2023\/04\/13\/01\/26\/15\/107124000_p0_master1200.jpg"}