{"pid":107528872,"p":1,"uid":10291992,"title":"one does not dream of bunny Toki","author":"CHARK","r18":true,"width":1984,"height":2806,"tags":["R-18","BlueArchive","ブルーアーカイブ","碧蓝档案","飛鳥馬トキ","飞鸟马时","飛鳥馬トキ(バニーガール)","飞鸟马时（兔女郎）","ブルアカ","トキ","Toki","バニーガール","兔女郎","バニー","bunny","揉みしだきたい乳","诱人把玩的乳房"],"ext":"jpg","aiType":1,"uploadDate":1682446589000,"urls":{"regular":"https:\/\/i.pixiv.re\/img-master\/img\/2023\/04\/26\/03\/16\/29\/107528872_p1_master1200.jpg"},"url":"\/img-master\/img\/2023\/04\/26\/03\/16\/29\/107528872_p1_master1200.jpg"}