{"pid":107786544,"p":0,"uid":17113161,"title":"《你就是猎手的新成员吗》银狼 Silver Wolf 은랑","author":"晰帅Sama","r18":true,"width":1882,"height":3900,"tags":["R-18","银狼","Silver Wolf","은랑","崩坏:星穹铁道","Honkai: Star Rail","極上の女体","极上女体","魅惑のふともも","魅惑的大腿","魅惑の谷間","魅惑的乳沟","極上の乳","极上乳房","巨乳","large breasts","おっぱい","欧派"],"ext":"jpg","aiType":2,"uploadDate":1683130963000,"urls":{"regular":"https:\/\/i.pixiv.re\/img-master\/img\/2023\/05\/04\/01\/22\/43\/107786544_p0_master1200.jpg"},"url":"\/img-master\/img\/2023\/05\/04\/01\/22\/43\/107786544_p0_master1200.jpg"}