{"pid":108044299,"p":0,"uid":87616168,"title":"『原神\/Genshin impact』Ganyu","author":"Lucy","r18":true,"width":2160,"height":3840,"tags":["R-18","AIイラスト","ai绘图","NovelAI","StableDiffusion","原神","Genshin Impact","GenshinImpact","魅惑の谷間","魅惑的乳沟","魅惑のふともも","魅惑的大腿"],"ext":"png","aiType":2,"uploadDate":1683821123000,"urls":{"regular":"https:\/\/i.pixiv.re\/img-master\/img\/2023\/05\/12\/01\/05\/23\/108044299_p0_master1200.jpg"},"url":"\/img-master\/img\/2023\/05\/12\/01\/05\/23\/108044299_p0_master1200.jpg"}