{"pid":108677984,"p":0,"uid":28638684,"title":"Asta","author":"AztoDio","r18":true,"width":570,"height":900,"tags":["R-18","崩坏星穹铁道","Honkai: Star Rail","崩壊スターレイル","崩坏：星穹铁道","アスター(スターレイル)","艾丝妲（星穹铁道）","すっぽんぽん","buck naked","揉みしだきたい乳","诱人把玩的乳房","極上の乳","极上乳房","AI","AI生成","AI-Generated"],"ext":"jpg","aiType":1,"uploadDate":1685751771000,"urls":{"regular":"https:\/\/i.pixiv.re\/img-master\/img\/2023\/06\/03\/09\/22\/51\/108677984_p0_master1200.jpg"},"url":"\/img-master\/img\/2023\/06\/03\/09\/22\/51\/108677984_p0_master1200.jpg"}