{"pid":108921233,"p":1,"uid":89129423,"title":"Smile \/\/ Kafka","author":"Apel | AI Art","r18":true,"width":960,"height":1280,"tags":["R-18","カフカ(スターレイル)","卡芙卡（星穹铁道）","崩坏星穹铁道","Honkai: Star Rail","魅惑のふともも","魅惑的大腿","Girl","ランジェリー","女式内衣","ネグリジェ","negligee","お尻","臀部"],"ext":"png","aiType":2,"uploadDate":1686468823000,"urls":{"regular":"https:\/\/i.pixiv.re\/img-master\/img\/2023\/06\/11\/16\/33\/43\/108921233_p1_master1200.jpg"},"url":"\/img-master\/img\/2023\/06\/11\/16\/33\/43\/108921233_p1_master1200.jpg"}