{"pid":109276280,"p":1,"uid":10291992,"title":"Othello","author":"CHARK","r18":true,"width":1587,"height":1122,"tags":["R-18","nsfw","NIKKE","勝利の女神:NIKKE","NIKKE：胜利女神","メガニケ","Goddess of Victory: Nikke","バニースーツ","兔女郎服饰","バニー","bunny","ブラン(勝利の女神:NIKKE)","Blanc (NIKKE: The Goddess of Victory)","ノワール(勝利の女神:NIKKE)","777(勝利の女神:NIKKE)","777 (NIKKE: The Goddess of Victory)"],"ext":"jpg","aiType":1,"uploadDate":1687524095000,"urls":{"regular":"https:\/\/i.pixiv.re\/img-master\/img\/2023\/06\/23\/21\/41\/35\/109276280_p1_master1200.jpg"},"url":"\/img-master\/img\/2023\/06\/23\/21\/41\/35\/109276280_p1_master1200.jpg"}