{"pid":109288208,"p":0,"uid":35688828,"title":"RaidenShogun sex6 R-18","author":"bright sky","r18":true,"width":1567,"height":1920,"tags":["R-18","雷電将軍","Raiden Shogun","原神","Genshin Impact","GenshinImpact","雷电将军","魅惑のふともも","魅惑的大腿","女の子","女孩子","Genshin","AI","RaidenShogun"],"ext":"jpg","aiType":2,"uploadDate":1687554116000,"urls":{"regular":"https:\/\/i.pixiv.re\/img-master\/img\/2023\/06\/24\/06\/01\/56\/109288208_p0_master1200.jpg"},"url":"\/img-master\/img\/2023\/06\/24\/06\/01\/56\/109288208_p0_master1200.jpg"}