{"pid":109946539,"p":1,"uid":6491712,"title":"バニーアスナぱい","author":"イブリオン","r18":true,"width":2475,"height":4389,"tags":["R-18","ブルーアーカイブ","碧蓝档案","ブルアカ","一之瀬アスナ","Asuna Ichinose","一之瀬アスナ(バニーガール)","Asuna Ichinose (bunny girl)","バニーガール","兔女郎","巨乳","large breasts","船上のバニーチェイサー","Bunny Chaser on Board","黒ストッキング","黑色丝袜"],"ext":"png","aiType":1,"uploadDate":1689433727000,"urls":{"regular":"https:\/\/i.pixiv.re\/img-master\/img\/2023\/07\/16\/00\/08\/47\/109946539_p1_master1200.jpg"},"url":"\/img-master\/img\/2023\/07\/16\/00\/08\/47\/109946539_p1_master1200.jpg"}