{"pid":110353799,"p":0,"uid":3403329,"title":"暑くてたまらないトウコさん。","author":"がっちゃん(残部ロッタ)","r18":true,"width":5081,"height":6071,"tags":["R-18","ポケモン人間絵","宝可梦人类角色","トウコ(トレーナー)","透子（训练家）","スポーツブラ","sports bra","ぱんつ","胖次","スポーツショーツ","蒸れ","stuffy","おっぱい","欧派","トウコっぱい","Hilda's breasts"],"ext":"png","aiType":1,"uploadDate":1690643001000,"urls":{"regular":"https:\/\/i.pixiv.re\/img-master\/img\/2023\/07\/30\/00\/03\/21\/110353799_p0_master1200.jpg"},"url":"\/img-master\/img\/2023\/07\/30\/00\/03\/21\/110353799_p0_master1200.jpg"}