{"pid":111130684,"p":2,"uid":67043637,"title":"一柳 梨璃x楓・J・ヌーベル  yuri request","author":"AZQ","r18":true,"width":1920,"height":2928,"tags":["R-18","AIイラスト","AI 画作","百合","yuri","百合キス","lesbian kiss","アサルトリリィ","突击莉莉","一柳梨璃","Riri Hitotsuyanagi","楓・J・ヌーベル","枫·J·努韦尔"],"ext":"png","aiType":2,"uploadDate":1692890242000,"urls":{"regular":"https:\/\/i.pixiv.re\/img-master\/img\/2023\/08\/25\/00\/17\/22\/111130684_p2_master1200.jpg"},"url":"\/img-master\/img\/2023\/08\/25\/00\/17\/22\/111130684_p2_master1200.jpg"}