{"pid":111334338,"p":0,"uid":71723824,"title":"ハナコ","author":"Doco","r18":true,"width":900,"height":1388,"tags":["R-18","ブルーアーカイブ","碧蓝档案","BlueArchive","urawahanako","ハナコ","Pansy","浦和ハナコ","Urawa Hanako","浦和ハナコ(水着)","浦和花子（泳装）","巨乳小学生","elementary schoolgirl with huge breasts"],"ext":"jpg","aiType":1,"uploadDate":1693494136000,"urls":{"regular":"https:\/\/i.pixiv.re\/img-master\/img\/2023\/09\/01\/00\/02\/16\/111334338_p0_master1200.jpg"},"url":"\/img-master\/img\/2023\/09\/01\/00\/02\/16\/111334338_p0_master1200.jpg"}