{"pid":111742381,"p":0,"uid":5587361,"title":"桃華の特製シャンパン","author":"ラマンダ","r18":true,"width":4299,"height":6071,"tags":["R-18","櫻井桃華","Momoka Sakurai","おしっこ","撒尿","聖水","golden shower","アイドルマスターシンデレラガールズ","偶像大师 灰姑娘女孩","マイクロビキニ","极小比基尼","水着","泳装","エロ蹲踞","H开腿","ずらし放尿"],"ext":"png","aiType":1,"uploadDate":1694776288000,"urls":{"regular":"https:\/\/i.pixiv.re\/img-master\/img\/2023\/09\/15\/20\/11\/28\/111742381_p0_master1200.jpg"},"url":"\/img-master\/img\/2023\/09\/15\/20\/11\/28\/111742381_p0_master1200.jpg"}