{"pid":111895990,"p":5,"uid":64101854,"title":"092123","author":"rororo","r18":true,"width":2894,"height":4093,"tags":["R-18","宮本武蔵(Fate)","宫本武藏 (Fate)","Fate\/GrandOrder","命运－冠位指定","FGO","Fate\/Grand Order","宮本武蔵(水着)","宫本武藏（泳装）","男主武","裸","nude","腋","腋下"],"ext":"jpg","aiType":1,"uploadDate":1695226742000,"urls":{"regular":"https:\/\/i.pixiv.re\/img-master\/img\/2023\/09\/21\/01\/19\/02\/111895990_p5_master1200.jpg"},"url":"\/img-master\/img\/2023\/09\/21\/01\/19\/02\/111895990_p5_master1200.jpg"}