{"pid":112009475,"p":0,"uid":848240,"title":"【差分５０枚】ベットの上で青君とハラマセックスCG集❤","author":"ディッコ","r18":true,"width":1897,"height":2846,"tags":["R-18","ホロライブ","Hololive","火威青","Hiodoshi Ao","肋骨","ribs","腋","腋下","おっぱいのついたイケメン","有胸的帅哥","イケメン女子","handsome girl","揉みしだきたい乳","诱人把玩的乳房","えちくゆ"],"ext":"jpg","aiType":1,"uploadDate":1695567676000,"urls":{"regular":"https:\/\/i.pixiv.re\/img-master\/img\/2023\/09\/25\/00\/01\/16\/112009475_p0_master1200.jpg"},"url":"\/img-master\/img\/2023\/09\/25\/00\/01\/16\/112009475_p0_master1200.jpg"}