{"pid":112976717,"p":0,"uid":11835289,"title":"ブローニャ・ザイチク","author":"fenbao","r18":true,"width":1200,"height":1667,"tags":["R-18","崩壊3rd","崩坏3rd","崩坏3","ブローニャ・ザイチク","布洛妮娅·扎伊切克","布洛妮娅","Bronya Zaychik","巨乳","large breasts","極上の乳","极上乳房","髪留め以外完全裸","发夹以外完全裸体"],"ext":"jpg","aiType":1,"uploadDate":1698654960000,"urls":{"regular":"https:\/\/i.pixiv.re\/img-master\/img\/2023\/10\/30\/17\/36\/00\/112976717_p0_master1200.jpg"},"url":"\/img-master\/img\/2023\/10\/30\/17\/36\/00\/112976717_p0_master1200.jpg"}