{"pid":113383056,"p":4,"uid":35688828,"title":"Danmachi Hestia R18","author":"bright sky","r18":true,"width":2400,"height":2664,"tags":["R-18","Danmachi","Hestia","女の子","女孩子","AI","ダンまち","期待在地下城邂逅有错吗","ダンジョンに出会いを求めるのは間違っているだろうか","在地下城寻求邂逅是否搞错了什么","ヘスティア","赫斯提亚"],"ext":"jpg","aiType":2,"uploadDate":1699875723000,"urls":{"regular":"https:\/\/i.pixiv.re\/img-master\/img\/2023\/11\/13\/20\/42\/03\/113383056_p4_master1200.jpg"},"url":"\/img-master\/img\/2023\/11\/13\/20\/42\/03\/113383056_p4_master1200.jpg"}