{"pid":113871946,"p":0,"uid":16309372,"title":"【Skeb】フリント","author":"Gino","r18":true,"width":1131,"height":1600,"tags":["R-18","アークナイツ","明日方舟","Arknights","フリント(アークナイツ)","燧石（明日方舟）","燧石","flint","産卵","产卵","破れタイツ","破损的丝袜","白タイツ","白裤袜","褐色","小麦色","リーベリ卵生説"],"ext":"jpg","aiType":1,"uploadDate":1701442801000,"urls":{"regular":"https:\/\/i.pixiv.re\/img-master\/img\/2023\/12\/02\/00\/00\/01\/113871946_p0_master1200.jpg"},"url":"\/img-master\/img\/2023\/12\/02\/00\/00\/01\/113871946_p0_master1200.jpg"}