{"pid":113862638,"p":0,"uid":2328,"title":"クレジッタさん美味しそうですね！","author":"RYUKI","r18":true,"width":1200,"height":800,"tags":["R-18","プリンセスコネクト!Re:Dive","公主连结Re:Dive","プリコネ","公主连结","ペコリーヌ","贪吃佩可","クレジッタ(プリコネ)","Creditta (Princess Connect)","母乳","breast milk","クレジッタ・キャッシュ","Creditta Cash","おっぱい","欧派","百合","yuri"],"ext":"jpg","aiType":1,"uploadDate":1701423480000,"urls":{"regular":"https:\/\/i.pixiv.re\/img-master\/img\/2023\/12\/01\/18\/38\/00\/113862638_p0_master1200.jpg"},"url":"\/img-master\/img\/2023\/12\/01\/18\/38\/00\/113862638_p0_master1200.jpg"}