{"pid":114150766,"p":10,"uid":3316400,"title":"わんわんプリズママイクロビキニ部","author":"MだSたろう","r18":true,"width":3146,"height":2096,"tags":["R-18","Fate\/GrandOrder","プリズマ☆イリヤ","魔法少女☆伊莉雅","イリヤスフィール・フォン・アインツベルン","伊莉雅丝菲尔・冯・爱因兹贝伦","クロエ・フォン・アインツベルン","克洛伊・冯・爱因兹贝伦","美遊・エーデルフェルト","美游·艾德费尔特","種付け","种付","中出し","中出","分身","clone yourself"],"ext":"jpg","aiType":1,"uploadDate":1702307076000,"urls":{"regular":"https:\/\/i.pixiv.re\/img-master\/img\/2023\/12\/12\/00\/04\/36\/114150766_p10_master1200.jpg"},"url":"\/img-master\/img\/2023\/12\/12\/00\/04\/36\/114150766_p10_master1200.jpg"}