{"pid":114299247,"p":1,"uid":92344897,"title":"La pluma. Swimsuit!! SO PRREtty!","author":"VillainChin","r18":true,"width":1710,"height":2500,"tags":["R-18","巨乳","large breasts","ラ・プルマ(アークナイツ)","羽毛笔（明日方舟）","酔っ払い","drunk","アークナイツ","明日方舟","水着","泳装","オナニー","自慰","垂れ愛液","ヌルテカ"],"ext":"jpg","aiType":1,"uploadDate":1702781190000,"urls":{"regular":"https:\/\/i.pixiv.re\/img-master\/img\/2023\/12\/17\/11\/46\/30\/114299247_p1_master1200.jpg"},"url":"\/img-master\/img\/2023\/12\/17\/11\/46\/30\/114299247_p1_master1200.jpg"}