{"pid":114646666,"p":1,"uid":6730789,"title":"キアサージ&ヒンデンブルク R18 version","author":"勇者＜M型＞","r18":true,"width":1200,"height":1411,"tags":["R-18","アズールレーン","碧蓝航线","Azur Lane","ヒンデンブルク(アズールレーン)","兴登堡（碧蓝航线）","キアサージ(アズールレーン)","奇尔沙治（碧蓝航线）","巨乳","large breasts","魅惑の谷間","魅惑的乳沟","陥没乳首","内陷乳头","バニーガール","兔女郎","爆乳","huge breasts"],"ext":"jpg","aiType":1,"uploadDate":1703788461000,"urls":{"regular":"https:\/\/i.pixiv.re\/img-master\/img\/2023\/12\/29\/03\/34\/21\/114646666_p1_master1200.jpg"},"url":"\/img-master\/img\/2023\/12\/29\/03\/34\/21\/114646666_p1_master1200.jpg"}