{"pid":115056480,"p":0,"uid":102119352,"title":"莱伊","author":"juejue二号机","r18":true,"width":2894,"height":4601,"tags":["R-18","アークナイツ","明日方舟","女の子","女孩子","巨乳","large breasts","莱伊","Ray","Arknights","レイ(アークナイツ)","Ray (Arknights)","AI","AI生成","AI-Generated"],"ext":"jpg","aiType":0,"uploadDate":1704885435000,"urls":{"regular":"https:\/\/i.pixiv.re\/img-master\/img\/2024\/01\/10\/20\/17\/15\/115056480_p0_master1200.jpg"},"url":"\/img-master\/img\/2024\/01\/10\/20\/17\/15\/115056480_p0_master1200.jpg"}