{"pid":115679819,"p":1,"uid":40716915,"title":"抱着杏杏睡大觉","author":"杏行为 火曜東D12b冬コミ","r18":true,"width":1840,"height":1280,"tags":["R-18","崩坏学园2","Gun Girls School DayZ","杏玛尔","杏·玛尔","シン・マール","Sin Mal","崩坏3rd","崩坏3","崩壊学園","崩坏学园","魅惑のふともも","魅惑的大腿","抱き枕","抱枕","貧乳","平胸"],"ext":"png","aiType":1,"uploadDate":1706800132000,"urls":{"regular":"https:\/\/i.pixiv.re\/img-master\/img\/2024\/02\/02\/00\/08\/52\/115679819_p1_master1200.jpg"},"url":"\/img-master\/img\/2024\/02\/02\/00\/08\/52\/115679819_p1_master1200.jpg"}