{"pid":116922982,"p":1,"uid":569672,"title":"朝活","author":"ミルクセーキ","r18":true,"width":1946,"height":1331,"tags":["R-18","ブルーアーカイブ","碧蓝档案","小鳥遊ホシノ","Takanashi Hoshino","腕掴みバック","ヘテロクロミア","heterochromia","後背位","后入式","全裸","completely naked","援助交際","enjo kosai"],"ext":"jpg","aiType":1,"uploadDate":1710428449000,"urls":{"regular":"https:\/\/i.pixiv.re\/img-master\/img\/2024\/03\/15\/00\/00\/49\/116922982_p1_master1200.jpg"},"url":"\/img-master\/img\/2024\/03\/15\/00\/00\/49\/116922982_p1_master1200.jpg"}