{"pid":117665008,"p":0,"uid":1348115,"title":"召命の神弓-アポロウーサ","author":"Ro_G","r18":true,"width":2000,"height":2829,"tags":["R-18","遊戯王OCG","游戏王OCG","召命の神弓-アポロウーサ","Apollousa, Bow of the Goddess","遊戯王女キャラ","女オナニー","女性自慰","ふともも","大腿","尻","屁股","目がハート","眼睛爱心"],"ext":"jpg","aiType":1,"uploadDate":1712570254000,"urls":{"regular":"https:\/\/i.pixiv.re\/img-master\/img\/2024\/04\/08\/18\/57\/34\/117665008_p0_master1200.jpg"},"url":"\/img-master\/img\/2024\/04\/08\/18\/57\/34\/117665008_p0_master1200.jpg"}