{"pid":119651321,"p":0,"uid":3793860,"title":"これはGWの時に描いたゴールデンアメス様❤","author":"aono","r18":true,"width":1820,"height":2404,"tags":["R-18","プリンセスコネクト!Re:Dive","公主连结Re:Dive","プリコネR","公主连结","アメス","爱莓斯","アメス(プリコネ)","爱梅斯（公主连结）","アメス様","お尻","臀部","おっぱい","欧派","I字バランス","站立一字马","スリングショット","弹弓"],"ext":"jpg","aiType":1,"uploadDate":1718417677000,"urls":{"regular":"https:\/\/i.pixiv.re\/img-master\/img\/2024\/06\/15\/11\/14\/37\/119651321_p0_master1200.jpg"},"url":"\/img-master\/img\/2024\/06\/15\/11\/14\/37\/119651321_p0_master1200.jpg"}