{"pid":120482229,"p":1,"uid":33148844,"title":"Untitled","author":"eseARU","r18":true,"width":1558,"height":1616,"tags":["R-18","绝区零","Zenless Zone Zero","ゼンレスゾーンゼロ","ルーシー","Lucy","パイパー・ウィール","ZenlessZoneZero","お腹","腹部","ルシアーナ・オクシスィース・テオドロ・デ・モンテフィーノ","露西亚娜·奥克希斯·提奥多·德·蒙特夫","裸足","赤脚"],"ext":"png","aiType":1,"uploadDate":1720831868000,"urls":{"regular":"https:\/\/i.pixiv.re\/img-master\/img\/2024\/07\/13\/09\/51\/08\/120482229_p1_master1200.jpg"},"url":"\/img-master\/img\/2024\/07\/13\/09\/51\/08\/120482229_p1_master1200.jpg"}