{"pid":120524396,"p":2,"uid":102831195,"title":"無題","author":"nana","r18":true,"width":832,"height":1216,"tags":["R-18","腋","腋下","腋見せのポーズ","Showing off armpits","ブルーアーカイブ","碧蓝档案","鬼方カヨコ","Onikata Kayoko","ブルアカ","BlueArchive","女の子","女孩子","鬼方カヨコ(ドレス)","Onikata Kayoko (Dress)","魅惑の谷間","魅惑的乳沟"],"ext":"jpg","aiType":2,"uploadDate":1720949407000,"urls":{"regular":"https:\/\/i.pixiv.re\/img-master\/img\/2024\/07\/14\/18\/30\/07\/120524396_p2_master1200.jpg"},"url":"\/img-master\/img\/2024\/07\/14\/18\/30\/07\/120524396_p2_master1200.jpg"}