{"pid":122265283,"p":0,"uid":86963643,"title":"神里绫华","author":"辉夜姬","r18":true,"width":2560,"height":3712,"tags":["R-18","原神","Genshin Impact","GenshinImpact","Genshin","神里绫华(原神)","Kamisato Ayaka (Genshin Impact)","神里綾華(原神)","神里绫华","Kamisato Ayaka","神里綾華","Ayaka Kamisato","極上の女体","极上女体","魅惑の谷間","魅惑的乳沟"],"ext":"jpg","aiType":2,"uploadDate":1725807633000,"urls":{"regular":"https:\/\/i.pixiv.re\/img-master\/img\/2024\/09\/09\/00\/00\/33\/122265283_p0_master1200.jpg"},"url":"\/img-master\/img\/2024\/09\/09\/00\/00\/33\/122265283_p0_master1200.jpg"}