{"pid":122617969,"p":0,"uid":17696303,"title":"靈砂·お風呂","author":"八重嘤嘤桜","r18":true,"width":1664,"height":2432,"tags":["R-18","崩壊スターレイル","崩坏：星穹铁道","崩坏星穹铁道","Honkai: Star Rail","霊砂","灵砂","極上の女体","极上女体","全裸","completely naked","お風呂","洗澡","巨乳","large breasts"],"ext":"png","aiType":2,"uploadDate":1726844440000,"urls":{"regular":"https:\/\/i.pixiv.re\/img-master\/img\/2024\/09\/21\/00\/00\/40\/122617969_p0_master1200.jpg"},"url":"\/img-master\/img\/2024\/09\/21\/00\/00\/40\/122617969_p0_master1200.jpg"}