{"pid":123911821,"p":0,"uid":361249,"title":"机の下の神州丸君","author":"とりさん","r18":true,"width":2400,"height":3200,"tags":["R-18","艦隊これくしょん","舰队collection","神州丸(艦隊これくしょん)","神州丸(舰队收藏)","島風の服","岛风的衣服","エロ蹲踞","H开腿","フェラ素振り","空气口交","目がハート","眼睛爱心","島風服艦娘(特務艦級)","ぱんつ","胖次"],"ext":"jpg","aiType":1,"uploadDate":1730491201000,"urls":{"regular":"https:\/\/i.pixiv.re\/img-master\/img\/2024\/11\/02\/05\/00\/01\/123911821_p0_master1200.jpg"},"url":"\/img-master\/img\/2024\/11\/02\/05\/00\/01\/123911821_p0_master1200.jpg"}