{"pid":124263037,"p":0,"uid":18664714,"title":"白熱する女の子同士のエッチ攻撃！　レズバトルの勝敗は！？","author":"GC3","r18":true,"width":1920,"height":1080,"tags":["R-18","百合","yuri","レズバトル","百合格鬥","半脱ぎ","脱到一半","ブラジャー","胸罩","パンツ","内裤","手マン","抠抠","ツインテール","双马尾","ぱんつ","胖次","腿","thighs"],"ext":"jpg","aiType":1,"uploadDate":1731497547000,"urls":{"regular":"https:\/\/i.pixiv.re\/img-master\/img\/2024\/11\/13\/20\/32\/27\/124263037_p0_master1200.jpg"},"url":"\/img-master\/img\/2024\/11\/13\/20\/32\/27\/124263037_p0_master1200.jpg"}