{"pid":124431199,"p":0,"uid":43400779,"title":"久しぶりにイレイナさん","author":"toeri","r18":true,"width":919,"height":1473,"tags":["R-18","魔女の旅々","魔女之旅","イレイナ","伊蕾娜","全裸","completely naked","おっぱい","欧派","ちっぱい","贫乳","赤面","脸红","乳寄せ","boobs squeezing","貧乳","平胸","パイパン","白虎"],"ext":"png","aiType":1,"uploadDate":1731943791000,"urls":{"regular":"https:\/\/i.pixiv.re\/img-master\/img\/2024\/11\/19\/00\/29\/51\/124431199_p0_master1200.jpg"},"url":"\/img-master\/img\/2024\/11\/19\/00\/29\/51\/124431199_p0_master1200.jpg"}