{"pid":125386106,"p":0,"uid":14225123,"title":"能代 風紀","author":"URDha","r18":true,"width":1536,"height":1088,"tags":["R-18","AI-assisted","能代(アズールレーン)","Noshiro (Azur Lane)","能代","Noshiro","アズールレーン","碧蓝航线","Azur Lane","敗北","败北","女子高生","女高中生","拘束","束缚","ボールギャグ","口塞"],"ext":"jpg","aiType":1,"uploadDate":1734767788000,"urls":{"regular":"https:\/\/i.pixiv.re\/img-master\/img\/2024\/12\/21\/16\/56\/28\/125386106_p0_master1200.jpg"},"url":"\/img-master\/img\/2024\/12\/21\/16\/56\/28\/125386106_p0_master1200.jpg"}