{"pid":125391897,"p":0,"uid":1060786,"title":"モルガン陛下","author":"うな丼：新作漫画配信中！","r18":true,"width":827,"height":1169,"tags":["R-18","FGO","Fate\/Grand Order","Fate\/GrandOrder","命运－冠位指定","モルガン(Fate)","Morgan (Fate)","メスの顔","发情脸","メスミスト","爆乳","huge breasts","赤面","脸红","むちむち","丰满","私がプレゼント"],"ext":"png","aiType":1,"uploadDate":1734779525000,"urls":{"regular":"https:\/\/i.pixiv.re\/img-master\/img\/2024\/12\/21\/20\/12\/05\/125391897_p0_master1200.jpg"},"url":"\/img-master\/img\/2024\/12\/21\/20\/12\/05\/125391897_p0_master1200.jpg"}