{"pid":127839341,"p":0,"uid":43383935,"title":"小鳥遊ホシノ","author":"升天","r18":true,"width":1618,"height":3004,"tags":["R-18","ブルーアーカイブ","碧蓝档案","ブルアカ","小鳥遊ホシノ","Takanashi Hoshino","裸","nude","アホ毛","ahoge","ちっぱい","贫乳","肋骨","ribs","風呂上がり","after bathing","ピンク髪","粉色头发"],"ext":"png","aiType":1,"uploadDate":1741014019000,"urls":{"regular":"https:\/\/i.pixiv.re\/img-master\/img\/2025\/03\/04\/00\/00\/19\/127839341_p0_master1200.jpg"},"url":"\/img-master\/img\/2025\/03\/04\/00\/00\/19\/127839341_p0_master1200.jpg"}