{"pid":128459009,"p":1,"uid":8217405,"title":"エルフメイドちゃんの苗床化調教","author":"アレンス","r18":true,"width":6000,"height":4000,"tags":["R-18","女の子","女孩子","肉壁","wall made of flesh","触手","tentacle","精液風呂","精液浴","M字開脚","M字开腿","肉空間","ぱんつ","胖次","苗床","seedbed","首輪","项圈"],"ext":"jpg","aiType":1,"uploadDate":1742566075000,"urls":{"regular":"https:\/\/i.pixiv.re\/img-master\/img\/2025\/03\/21\/23\/07\/55\/128459009_p1_master1200.jpg"},"url":"\/img-master\/img\/2025\/03\/21\/23\/07\/55\/128459009_p1_master1200.jpg"}