{"pid":132044357,"p":0,"uid":14647672,"title":"ミネハメ自撮り","author":"塞翁が牛","r18":true,"width":3944,"height":3358,"tags":["R-18","BlueArchive","ブルーアーカイブ","碧蓝档案","ブルアカ","蒼森ミネ","苍森美弥","寝バック","俯卧后入","ハメピス","キスマーク","hickey","メスミスト","つぶれおっぱい","collapsed breasts"],"ext":"png","aiType":1,"uploadDate":1751036413000,"urls":{"regular":"https:\/\/i.pixiv.re\/img-master\/img\/2025\/06\/28\/00\/00\/13\/132044357_p0_master1200.jpg"},"url":"\/img-master\/img\/2025\/06\/28\/00\/00\/13\/132044357_p0_master1200.jpg"}