{"pid":133751541,"p":0,"uid":44906939,"title":"美遊ちゃん落書き","author":"むむむ星人","r18":true,"width":2508,"height":3541,"tags":["R-18","拘束","束缚","緊縛","紧缚","開口器","open mouth gag","美遊・エーデルフェルト","美游·艾德费尔特","プリズマ☆イリヤ","魔法少女☆伊莉雅","猿轡","猿辔","黑髮","black hair","汗","sweat"],"ext":"jpg","aiType":1,"uploadDate":1754892810000,"urls":{"regular":"https:\/\/i.pixiv.re\/img-master\/img\/2025\/08\/11\/15\/13\/30\/133751541_p0_master1200.jpg"},"url":"\/img-master\/img\/2025\/08\/11\/15\/13\/30\/133751541_p0_master1200.jpg"}