{"pid":134259702,"p":0,"uid":91325601,"title":"グレイフィア・ルキフグス - メイドの務め","author":"Setsu","r18":true,"width":1280,"height":1856,"tags":["R-18","グレイフィア・ルキフグス","葛瑞菲雅·路基弗古斯","ハイスクールD×D","恶魔高校D×D","evaEffect","魅惑のふともも","魅惑的大腿","極上の女体","极上女体","極上の乳","极上乳房","揉みしだきたい乳","诱人把玩的乳房","ねじ込みたい尻","这屁股让人想肛","むちむち","丰满"],"ext":"png","aiType":1,"uploadDate":1755992170000,"urls":{"regular":"https:\/\/i.pixiv.re\/img-master\/img\/2025\/08\/24\/08\/36\/10\/134259702_p0_master1200.jpg"},"url":"\/img-master\/img\/2025\/08\/24\/08\/36\/10\/134259702_p0_master1200.jpg"}