{"pid":134794809,"p":1,"uid":6500352,"title":"『 LINEKING Ⅲ 王の帰還』","author":"Sueスーエ","r18":true,"width":1600,"height":2262,"tags":["R-18","LINEKING","王の帰還","長手袋","长手套","猫耳","cat ears","ショートカット","短发","ビキニ","比基尼","M字開脚","M字开腿","爆乳","huge breasts","女の子","女孩子"],"ext":"jpg","aiType":1,"uploadDate":1757170824000,"urls":{"regular":"https:\/\/i.pixiv.re\/img-master\/img\/2025\/09\/07\/00\/00\/24\/134794809_p1_master1200.jpg"},"url":"\/img-master\/img\/2025\/09\/07\/00\/00\/24\/134794809_p1_master1200.jpg"}