{"pid":135472421,"p":0,"uid":90932536,"title":"バニートキと…","author":"Crowna","r18":true,"width":2800,"height":4096,"tags":["R-18","飛鳥馬トキ","飞鸟马时","ブルーアーカイブ","碧蓝档案","バニーガール","兔女郎","ブルアカ","飛鳥馬トキ(バニーガール)","飞鸟马时（兔女郎）","BlueArchive","トキ","Toki","おっぱい","欧派","極上の乳","极上乳房"],"ext":"jpg","aiType":2,"uploadDate":1758664833000,"urls":{"regular":"https:\/\/i.pixiv.re\/img-master\/img\/2025\/09\/24\/07\/00\/33\/135472421_p0_master1200.jpg"},"url":"\/img-master\/img\/2025\/09\/24\/07\/00\/33\/135472421_p0_master1200.jpg"}