{"pid":136780122,"p":0,"uid":86845153,"title":"ゼタ","author":"如墨","r18":true,"width":2032,"height":2984,"tags":["R-18","女の子","女孩子","揉みしだきたい乳","诱人把玩的乳房","極上の女体","极上女体","極上の乳","极上乳房","魅惑の谷間","魅惑的乳沟","露出","暴露","巨乳","large breasts","爆乳","huge breasts","GranblueFantasy"],"ext":"png","aiType":2,"uploadDate":1761579276000,"urls":{"regular":"https:\/\/i.pixiv.re\/img-master\/img\/2025\/10\/28\/00\/34\/36\/136780122_p0_master1200.jpg"},"url":"\/img-master\/img\/2025\/10\/28\/00\/34\/36\/136780122_p0_master1200.jpg"}