{"pid":140573998,"p":5,"uid":109707316,"title":"赛希","author":"Xiecr鱼","r18":true,"width":4864,"height":3328,"tags":["R-18","AI生成","AI-Generated","赛希","アークナイツ:エンドフィールド","明日方舟：终末地","舐め回したい穴","想舔到不行的穴","発情","发情","顔を埋めたい股間","想把脸埋进这两腿之间","揉みしだきたい乳","诱人把玩的乳房","快楽堕ち","沉浸快感","溢れ精液","精液溢出"],"ext":"jpg","aiType":1,"uploadDate":1769797690000,"urls":{"regular":"https:\/\/i.pixiv.re\/img-master\/img\/2026\/01\/31\/03\/28\/10\/140573998_p5_master1200.jpg"},"url":"\/img-master\/img\/2026\/01\/31\/03\/28\/10\/140573998_p5_master1200.jpg"}