{"pid":140893787,"p":0,"uid":31938023,"title":"ロンパオパオ","author":"Kokihanada","r18":true,"width":2894,"height":4093,"tags":["R-18","アークナイツ","明日方舟","Arknights","リィン(アークナイツ)","令（明日方舟）","シー(アークナイツ)","夕（明日方舟）","ニェン(アークナイツ)","年（明日方舟）","お尻","臀部","尻尾","尾巴","尻タワー","ass tower"],"ext":"jpg","aiType":1,"uploadDate":1770469776000,"urls":{"regular":"https:\/\/i.pixiv.re\/img-master\/img\/2026\/02\/07\/22\/09\/36\/140893787_p0_master1200.jpg"},"url":"\/img-master\/img\/2026\/02\/07\/22\/09\/36\/140893787_p0_master1200.jpg"}