{"pid":143510023,"p":0,"uid":1572851,"title":"レナ　肉壁拘束触手責め","author":"ゆにこかすみ","r18":true,"width":4206,"height":3168,"tags":["R-18","水波レナ","Rena Minami","マギレコ","Magia Record","マギアレコード","魔法纪录","全裸","completely naked","肉壁","wall made of flesh","触手","tentacle","中出し","中出"],"ext":"jpg","aiType":1,"uploadDate":1776075109000,"urls":{"regular":"https:\/\/i.pixiv.re\/img-master\/img\/2026\/04\/13\/19\/11\/49\/143510023_p0_master1200.jpg"},"url":"\/img-master\/img\/2026\/04\/13\/19\/11\/49\/143510023_p0_master1200.jpg"}