{"pid":146251740,"p":3,"uid":3485610,"title":"アニス：スター抱き枕","author":"憂凪あまね","r18":true,"width":1382,"height":1280,"tags":["R-18","勝利の女神:NIKKE","NIKKE：胜利女神","NIKKE","アニス(勝利の女神:NIKKE)","Anis (NIKKE: The Goddess of Victory)","アニス:スター","抱き枕","抱枕","巨乳","large breasts"],"ext":"jpg","aiType":1,"uploadDate":1781967651000,"urls":{"regular":"https:\/\/i.pixiv.re\/img-master\/img\/2026\/06\/21\/00\/00\/51\/146251740_p3_master1200.jpg"},"url":"\/img-master\/img\/2026\/06\/21\/00\/00\/51\/146251740_p3_master1200.jpg"}