{"pid":40929611,"p":0,"uid":63652,"title":"砲雷撃戦！よーい！6戦目　表紙","author":"中乃空","r18":true,"width":648,"height":906,"tags":["R-18","艦これ","舰C","阿賀野","Agano","砲雷撃戦!よーい!六戦目","マフィントップ","muffin top","艦隊これくしょん","舰队collection","艦ぱい","shipgirl breasts","乳神様","乳神大人","ぱんつ","胖次"],"ext":"jpg","aiType":0,"uploadDate":1389540891000,"urls":{"regular":"https:\/\/i.pixiv.re\/img-master\/img\/2014\/01\/13\/00\/34\/51\/40929611_p0_master1200.jpg"},"url":"\/img-master\/img\/2014\/01\/13\/00\/34\/51\/40929611_p0_master1200.jpg"}