{"pid":63671579,"p":0,"uid":7805672,"title":"三蔵","author":"奶凍","r18":true,"width":1293,"height":2047,"tags":["R-18","Fate\/GrandOrder","命运－冠位指定","Fate","FGO","Fate\/Grand Order","玄奘三蔵(Fate)","玄奘三藏(Fate)","パイパン","白虎","このおっぱいで聖女は無理でしょ","圣女不可能这么巨乳","性女","lascivious female saint","卍"],"ext":"jpg","aiType":0,"uploadDate":1498989942000,"urls":{"regular":"https:\/\/i.pixiv.re\/img-master\/img\/2017\/07\/02\/19\/05\/42\/63671579_p0_master1200.jpg"},"url":"\/img-master\/img\/2017\/07\/02\/19\/05\/42\/63671579_p0_master1200.jpg"}