{"pid":64084802,"p":2,"uid":848141,"title":"【新刊】Fate\/HO 予約開始しました","author":"ReBe_111H","r18":true,"width":1105,"height":1553,"tags":["R-18","Fate\/GrandOrder","巨乳","large breasts","新刊","new publication","アルトリア・ペンドラゴン","阿尔托利亚·潘德拉贡","キャス狐","C狐","スカサハ","斯卡哈","ネロ・クラウディウス","尼禄·克劳狄乌斯","マシュ・キリエライト","玛修·基列莱特"],"ext":"jpg","uploadDate":1501174843000,"urls":{"regular":"https:\/\/i.pixiv.re\/img-master\/img\/2017\/07\/28\/02\/00\/43\/64084802_p2_master1200.jpg"},"url":"\/img-master\/img\/2017\/07\/28\/02\/00\/43\/64084802_p2_master1200.jpg"}