{"pid":70083425,"p":0,"uid":8234278,"title":"白露姉","author":"pooor","r18":true,"width":713,"height":1024,"tags":["艦これ","舰C","艦隊これくしょん","舰队collection","白露","Shiratsuyu","白露(艦隊これくしょん)","白露(舰队Collection)","白露改二","下着艦娘","shipgirls in underwear","即夜戦","即将夜战","まったく、駆逐艦は最高だぜ!!","驱逐舰真是太棒了！","ぱんつ","胖次"],"ext":"jpg","aiType":0,"uploadDate":1533695378000,"urls":{"regular":"https:\/\/i.pixiv.re\/img-master\/img\/2018\/08\/08\/11\/29\/38\/70083425_p0_master1200.jpg"},"url":"\/img-master\/img\/2018\/08\/08\/11\/29\/38\/70083425_p0_master1200.jpg"}