{"pid":70643590,"p":1,"uid":20497976,"title":"咕嚕靈波（●´∀｀）ノ♡","author":"Luminous Art","r18":true,"width":1876,"height":2021,"tags":["R-18","女の子","女孩子","プリンセスコネクト!Re:Dive","公主连结Re:Dive","マホ","プリコネR","公主连结","マホ(プリコネ)","真步(公主连结)","ロリ","萝莉","落書き","涂鸦","獣耳","兽耳"],"ext":"jpg","aiType":0,"uploadDate":1536624964000,"urls":{"regular":"https:\/\/i.pixiv.re\/img-master\/img\/2018\/09\/11\/09\/16\/04\/70643590_p1_master1200.jpg"},"url":"\/img-master\/img\/2018\/09\/11\/09\/16\/04\/70643590_p1_master1200.jpg"}