{"pid":75706599,"p":0,"uid":3004090,"title":"セミラミス","author":"芝士糖","r18":true,"width":848,"height":1200,"tags":["R-18","セミラミス(Fate)","赛米拉米斯（Fate）","Fate\/GrandOrder","Fate\/Apocrypha","全裸","completely naked","足組み","跷二郎腿","裸足裏","裸足脚底","踏んでください","请踩我","魅惑のふともも","魅惑的大腿"],"ext":"jpg","aiType":0,"uploadDate":1563030010000,"urls":{"regular":"https:\/\/i.pixiv.re\/img-master\/img\/2019\/07\/14\/00\/00\/10\/75706599_p0_master1200.jpg"},"url":"\/img-master\/img\/2019\/07\/14\/00\/00\/10\/75706599_p0_master1200.jpg"}