{"pid":76427872,"p":0,"uid":4121985,"title":"一生懸命応えてくれる","author":"御幸やや","r18":true,"width":1414,"height":1000,"tags":["R-18","艦隊これくしょん","舰队collection","艦これ","舰C","満潮","Michishio","まったく、駆逐艦は最高だぜ!!","驱逐舰真是太棒了！","朝潮型はガチ","crazy for the Asashio-class girls","満潮(艦隊これくしょん)","Michishio (Kantai Collection)","裏提督LOVE勢","KanColle tsundere"],"ext":"jpg","aiType":0,"uploadDate":1566595251000,"urls":{"regular":"https:\/\/i.pixiv.re\/img-master\/img\/2019\/08\/24\/06\/20\/51\/76427872_p0_master1200.jpg"},"url":"\/img-master\/img\/2019\/08\/24\/06\/20\/51\/76427872_p0_master1200.jpg"}