{"pid":76966631,"p":0,"uid":4872213,"title":"ようちゃん","author":"N.G.","r18":true,"width":1000,"height":754,"tags":["R-18","渡辺曜","渡边曜","ラブライブ!サンシャイン!!","LoveLive! Sunshine!!","片乳","one breast exposed","競泳水着","竞技泳装","おっぱい","欧派","魅惑の谷間","魅惑的乳沟","魅惑のふともも","魅惑的大腿","おぱ曜","You's breast focus"],"ext":"jpg","aiType":0,"uploadDate":1569420161000,"urls":{"regular":"https:\/\/i.pixiv.re\/img-master\/img\/2019\/09\/25\/23\/02\/41\/76966631_p0_master1200.jpg"},"url":"\/img-master\/img\/2019\/09\/25\/23\/02\/41\/76966631_p0_master1200.jpg"}