{"pid":79282734,"p":0,"uid":3342599,"title":"FF34!!!","author":"凜凜魚","r18":true,"width":2551,"height":3579,"tags":["R-18","魅惑の谷間","魅惑的乳沟","氷川鏡華","Kyouka Hikawa","エロ衣装","H服装","剥ぎ取りたいブラ","让人想脱掉的胸罩","キョウカ(プリコネ)","镜华（公主连结）","プリンセスコネクト!Re:Dive","公主连结Re:Dive","裸足","赤脚","性印"],"ext":"jpg","aiType":0,"uploadDate":1580814129000,"urls":{"regular":"https:\/\/i.pixiv.re\/img-master\/img\/2020\/02\/04\/20\/02\/09\/79282734_p0_master1200.jpg"},"url":"\/img-master\/img\/2020\/02\/04\/20\/02\/09\/79282734_p0_master1200.jpg"}