{"pid":79986770,"p":1,"uid":6587511,"title":"アークナイツ (アーミヤ、エイヤフィヤトラ)","author":"トマトーゴ","r18":true,"width":1500,"height":2121,"tags":["アークナイツ","明日方舟","アーミヤ(アークナイツ)","阿米娅（明日方舟）","エイヤフィヤトラ(アークナイツ)","艾雅法拉(明日方舟)","R-18","阿米娅","Amiya","下着","内衣","生えかけ","first pubic hair","艾雅法拉","Eyjafjalla","ぱんつ","胖次"],"ext":"jpg","aiType":0,"uploadDate":1583675205000,"urls":{"regular":"https:\/\/i.pixiv.re\/img-master\/img\/2020\/03\/08\/22\/46\/45\/79986770_p1_master1200.jpg"},"url":"\/img-master\/img\/2020\/03\/08\/22\/46\/45\/79986770_p1_master1200.jpg"}