{"pid":82192507,"p":1,"uid":2886368,"title":"デンジャラス・ビースト美遊ちゃん","author":"とらいし６６６","r18":true,"width":872,"height":1200,"tags":["R-18","プリズマ☆イリヤ","魔法少女☆伊莉雅","FGO","Fate\/Grand Order","Fate\/GrandOrder","命运－冠位指定","美遊・エーデルフェルト","美游·艾德费尔特","デンジャラス・ビースト","危险野兽","催眠","Hypnosis","すじ","骆驼趾","鼠蹊部","groin"],"ext":"png","aiType":0,"uploadDate":1591629143000,"urls":{"regular":"https:\/\/i.pixiv.re\/img-master\/img\/2020\/06\/09\/00\/12\/23\/82192507_p1_master1200.jpg"},"url":"\/img-master\/img\/2020\/06\/09\/00\/12\/23\/82192507_p1_master1200.jpg"}