{"pid":82372359,"p":0,"uid":28838,"title":"シャロちゃんのえちえち自撮り","author":"りかたん☆","r18":true,"width":600,"height":836,"tags":["R-18","ご注文はうさぎですか?","请问您今天要来点兔子吗？","ごちうさ","点兔","シャロ","纱路","桐間紗路","桐间纱路","高品質パンツ","高品质内裤","撫で回したいお腹","让人想摸个够的肚子","極上の貧乳","极上贫乳","ぱんつ","胖次"],"ext":"jpg","aiType":0,"uploadDate":1592319605000,"urls":{"regular":"https:\/\/i.pixiv.re\/img-master\/img\/2020\/06\/17\/00\/00\/05\/82372359_p0_master1200.jpg"},"url":"\/img-master\/img\/2020\/06\/17\/00\/00\/05\/82372359_p0_master1200.jpg"}