{"pid":82594769,"p":0,"uid":3372346,"title":"(仕事絵)お帰りなさいませ、主様","author":"NC731","r18":true,"width":1158,"height":1637,"tags":["R-18","プリンセスコネクト!Re:Dive","公主连结Re:Dive","プリコネR","公主连结","百合","yuri","キャル","凯露","コッコロ","可可萝","ケモミミ","兽耳","オナニー","自慰","全裸","completely naked","仕事絵","商业绘图"],"ext":"jpg","aiType":0,"uploadDate":1593244649000,"urls":{"regular":"https:\/\/i.pixiv.re\/img-master\/img\/2020\/06\/27\/16\/57\/29\/82594769_p0_master1200.jpg"},"url":"\/img-master\/img\/2020\/06\/27\/16\/57\/29\/82594769_p0_master1200.jpg"}