{"pid":84156199,"p":0,"uid":1599160,"title":"プリヤ公衆便所","author":"冬蟲夏草","r18":true,"width":1344,"height":756,"tags":["R-18","凌辱","sexual assault","プリズマ☆イリヤ","魔法少女☆伊莉雅","肉便器","cum dump","Fate\/GrandOrder","命运－冠位指定","アへ顔","高潮脸","イリヤスフィール・フォン・アインツベルン","伊莉雅丝菲尔・冯・爱因兹贝伦","美遊・エーデルフェルト","美游·艾德费尔特","クロエ・フォン・アインツベルン","克洛伊・冯・爱因兹贝伦","拘束","束缚"],"ext":"jpg","aiType":0,"uploadDate":1599231612000,"urls":{"regular":"https:\/\/i.pixiv.re\/img-master\/img\/2020\/09\/05\/00\/00\/12\/84156199_p0_master1200.jpg"},"url":"\/img-master\/img\/2020\/09\/05\/00\/00\/12\/84156199_p0_master1200.jpg"}