{"pid":85842087,"p":0,"uid":12748307,"title":"囚われ苗床フランちゃん","author":"秋葉もなか","r18":true,"width":1064,"height":1169,"tags":["R-18","東方","东方","フランドール・スカーレット","芙兰朵露・斯卡蕾特","アナル","肛门","苗床","seedbed","触手","tentacle","理性を破壊する程度の能力","足以破坏理性的能力","破れタイツ","破损的丝袜","U.N.おっぱい","Flandre Scarlet's big breasts","M字開脚","M字开腿"],"ext":"png","aiType":0,"uploadDate":1606056903000,"urls":{"regular":"https:\/\/i.pixiv.re\/img-master\/img\/2020\/11\/22\/23\/55\/03\/85842087_p0_master1200.jpg"},"url":"\/img-master\/img\/2020\/11\/22\/23\/55\/03\/85842087_p0_master1200.jpg"}