{"pid":87216734,"p":0,"uid":2864095,"title":"Barbara chong ya","author":"MSK12003月曜日東C17","r18":true,"width":1100,"height":935,"tags":["R-18","巨乳","large breasts","原神","Genshin Impact","バーバラ(原神)","芭芭拉（原神）","まんぐり返し","抬腿露阴","足裏","脚底","ソックス足裏","着袜足底","白タイツ","白裤袜","揉みしだきたい乳","诱人把玩的乳房"],"ext":"png","aiType":0,"uploadDate":1611287993000,"urls":{"regular":"https:\/\/i.pixiv.re\/img-master\/img\/2021\/01\/22\/12\/59\/53\/87216734_p0_master1200.jpg"},"url":"\/img-master\/img\/2021\/01\/22\/12\/59\/53\/87216734_p0_master1200.jpg"}