{"pid":88134350,"p":1,"uid":11512980,"title":"또 너야?","author":"面倒くさい","r18":true,"width":2000,"height":2300,"tags":["R-18","maplestory","女の子","女孩子","スク水","学生泳衣","ローター","跳蛋","旧スク","old-fashioned school swimsuit","淫紋","淫纹","旧スク水","スク水ニーソ","school swimsuit with knee socks"],"ext":"png","aiType":0,"uploadDate":1614551741000,"urls":{"regular":"https:\/\/i.pixiv.re\/img-master\/img\/2021\/03\/01\/07\/35\/41\/88134350_p1_master1200.jpg"},"url":"\/img-master\/img\/2021\/03\/01\/07\/35\/41\/88134350_p1_master1200.jpg"}