{"pid":89073388,"p":0,"uid":7127962,"title":"互帮互助","author":"只有弱者才睡觉","r18":true,"width":1427,"height":1049,"tags":["R-18","紫咲シオン","紫咲诗音","潤羽るしあ","润羽露西娅","猫耳","cat ears","百合","yuri","ホロライブ","Hololive","しっぽリボン","tail with ribbon","裸足","赤脚","バーチャルYouTuber","虚拟主播"],"ext":"jpg","aiType":0,"uploadDate":1618080011000,"urls":{"regular":"https:\/\/i.pixiv.re\/img-master\/img\/2021\/04\/11\/03\/40\/11\/89073388_p0_master1200.jpg"},"url":"\/img-master\/img\/2021\/04\/11\/03\/40\/11\/89073388_p0_master1200.jpg"}