{"pid":89794261,"p":0,"uid":9446731,"title":"Lefiya Viridis","author":"Chr","r18":true,"width":1000,"height":1414,"tags":["レフィーヤ・ウィリディス","Lefiya Viridis","ダンまち","期待在地下城邂逅有错吗","ダンジョンに出会いを求めるのは間違っているだろうか","在地下城寻求邂逅是否搞错了什么","精液","semen","R-18","エルフ","精灵","エルフ耳","精灵耳"],"ext":"jpg","aiType":0,"uploadDate":1620825777000,"urls":{"regular":"https:\/\/i.pixiv.re\/img-master\/img\/2021\/05\/12\/22\/22\/57\/89794261_p0_master1200.jpg"},"url":"\/img-master\/img\/2021\/05\/12\/22\/22\/57\/89794261_p0_master1200.jpg"}