{"pid":89879793,"p":0,"uid":30481106,"title":"Xiang Ling Beach Chef","author":"Skai_kun","r18":true,"width":2894,"height":4093,"tags":["R-18","原神","Genshin Impact","GenshinImpact","水着","泳装","香菱(原神)","Xiangling (Genshin Impact)","女の子","女孩子","エプロン","围裙","おっぱい","欧派","裸エプロン","裸体围裙"],"ext":"jpg","aiType":0,"uploadDate":1621149969000,"urls":{"regular":"https:\/\/i.pixiv.re\/img-master\/img\/2021\/05\/16\/16\/26\/09\/89879793_p0_master1200.jpg"},"url":"\/img-master\/img\/2021\/05\/16\/16\/26\/09\/89879793_p0_master1200.jpg"}