{"pid":89926450,"p":0,"uid":35851079,"title":"桃鈴ねね","author":"いちごー\/鹿角伸","r18":true,"width":2508,"height":3541,"tags":["R-18","桃鈴ねね","桃铃音音","ホロライブ","Hololive","Vtuber","virtual YouTuber","バーチャルYouTuber","虚拟主播","騎乗位","骑乘位","中出し","中出","生まれたままの姿(産まれたままの姿)全裸(ヌード)","birthday suit","巨乳","large breasts"],"ext":"png","aiType":0,"uploadDate":1621324815000,"urls":{"regular":"https:\/\/i.pixiv.re\/img-master\/img\/2021\/05\/18\/17\/00\/15\/89926450_p0_master1200.jpg"},"url":"\/img-master\/img\/2021\/05\/18\/17\/00\/15\/89926450_p0_master1200.jpg"}