{"pid":90226406,"p":3,"uid":8406434,"title":"[No.46] イラストリアス (FANBOX 5月)","author":"みなわ","r18":true,"width":1280,"height":905,"tags":["R-18","アズールレーン","碧蓝航线","イラストリアス(アズールレーン)","光辉(碧蓝航线)","くぱぁ","掰穴","子宮口","子宫口","揉みしだきたい乳","诱人把玩的乳房","ぱんつ","胖次","立ちバック","站立后入"],"ext":"jpg","aiType":0,"uploadDate":1622451605000,"urls":{"regular":"https:\/\/i.pixiv.re\/img-master\/img\/2021\/05\/31\/18\/00\/05\/90226406_p3_master1200.jpg"},"url":"\/img-master\/img\/2021\/05\/31\/18\/00\/05\/90226406_p3_master1200.jpg"}