{"pid":90704909,"p":2,"uid":10415882,"title":"♥ Nhhhn ♥","author":"vahn_yourdoom","r18":true,"width":951,"height":1345,"tags":["R-18","催眠","Hypnosis","目がハート","眼睛爱心","ロゥリィ・マーキュリー","萝莉·麦丘利","自衛隊彼の地にて、斯く戦えり","奇幻自卫队","エロ衣装","H服装","洗脳","洗脑","下着","内衣","乳首ピアス","乳环","腋","腋下"],"ext":"jpg","aiType":0,"uploadDate":1624217869000,"urls":{"regular":"https:\/\/i.pixiv.re\/img-master\/img\/2021\/06\/21\/04\/37\/49\/90704909_p2_master1200.jpg"},"url":"\/img-master\/img\/2021\/06\/21\/04\/37\/49\/90704909_p2_master1200.jpg"}