{"pid":91226125,"p":0,"uid":161421,"title":"トリニティ総合学園・裸登校部","author":"しろすず◆二日目東Ｃ45b","r18":true,"width":858,"height":1200,"tags":["R-18","ブルーアーカイブ","碧蓝档案","ハナコ(ブルアカ)","コハル(ブルアカ)","浦和ハナコ","Urawa Hanako","下江コハル","補習授業部","Supplementary Lesson Department","揉みしだきたい乳","诱人把玩的乳房","全裸","completely naked"],"ext":"jpg","aiType":0,"uploadDate":1626188411000,"urls":{"regular":"https:\/\/i.pixiv.re\/img-master\/img\/2021\/07\/14\/00\/00\/11\/91226125_p0_master1200.jpg"},"url":"\/img-master\/img\/2021\/07\/14\/00\/00\/11\/91226125_p0_master1200.jpg"}