{"pid":92799564,"p":2,"uid":66239687,"title":"スキルを使用するライデン","author":"NABIN","r18":true,"width":1378,"height":2066,"tags":["R-18","GenshinImpact","Genshin","원신","原神","Genshin Impact","雷電将軍","Raiden Shogun","雷電将軍(原神)","Raiden Shogun (Genshin Impact)","パンツ","内裤","原尻","Genshin Ass","尻神様","尻神样"],"ext":"png","aiType":0,"uploadDate":1631822193000,"urls":{"regular":"https:\/\/i.pixiv.re\/img-master\/img\/2021\/09\/17\/04\/56\/33\/92799564_p2_master1200.jpg"},"url":"\/img-master\/img\/2021\/09\/17\/04\/56\/33\/92799564_p2_master1200.jpg"}