{"pid":93983369,"p":0,"uid":7203802,"title":"铃兰","author":"Shio","r18":true,"width":5000,"height":2924,"tags":["R-18","明日方舟","Arknights","铃兰","lily of the valley","盐风教主昆图斯","兽耳","animal ears","loli","触手","tentacle","中出","白丝","White silk pantyhose","スズラン(アークナイツ)","铃兰（明日方舟）"],"ext":"jpg","uploadDate":1636283333000,"urls":{"regular":"https:\/\/i.pixiv.re\/img-master\/img\/2021\/11\/07\/20\/08\/53\/93983369_p0_master1200.jpg"},"url":"\/img-master\/img\/2021\/11\/07\/20\/08\/53\/93983369_p0_master1200.jpg"}