{"pid":94645089,"p":1,"uid":4383668,"title":"イかせテクニック試験","author":"にど","r18":true,"width":913,"height":1217,"tags":["R-18","バーチャルYouTuber","虚拟主播","にじさんじ","彩虹社","リゼ・ヘルエスタ","莉泽·赫露艾斯塔","笹木咲","Saku Sasaki","常識改変","改变常识","催眠","Hypnosis","手マン","抠抠","つるまんさいこう","白虎太棒了"],"ext":"jpg","aiType":0,"uploadDate":1638947676000,"urls":{"regular":"https:\/\/i.pixiv.re\/img-master\/img\/2021\/12\/08\/16\/14\/36\/94645089_p1_master1200.jpg"},"url":"\/img-master\/img\/2021\/12\/08\/16\/14\/36\/94645089_p1_master1200.jpg"}