{"pid":94979384,"p":0,"uid":3382544,"title":"C99新刊「PRI CONNE MATOME」","author":"luft7star\/るふと七星","r18":true,"width":1123,"height":1600,"tags":["R-18","プリンセスコネクト!Re:Dive","公主连结Re:Dive","プリコネR","公主连结","C99","キャル(プリコネ)","凯露（公主连结）","キャル","凯露","ネネカ(プリコネ)","似似花（公主连结）","ミソギ(プリコネ)","未奏希（公主连结）","揉みしだきたい乳","诱人把玩的乳房"],"ext":"png","aiType":0,"uploadDate":1640336407000,"urls":{"regular":"https:\/\/i.pixiv.re\/img-master\/img\/2021\/12\/24\/18\/00\/07\/94979384_p0_master1200.jpg"},"url":"\/img-master\/img\/2021\/12\/24\/18\/00\/07\/94979384_p0_master1200.jpg"}