{"pid":95296679,"p":1,"uid":40586474,"title":"云堇","author":"Z282g","r18":true,"width":2268,"height":1516,"tags":["R-18","原神","Genshin Impact","genshinimpact","女の子","女孩子","魅惑のふともも","魅惑的大腿","直穿き","真空","失禁","incontinence","云堇","Yunjin","雲菫","Yun Jin","黒スト","黑丝袜"],"ext":"png","aiType":0,"uploadDate":1641291845000,"urls":{"regular":"https:\/\/i.pixiv.re\/img-master\/img\/2022\/01\/04\/19\/24\/05\/95296679_p1_master1200.jpg"},"url":"\/img-master\/img\/2022\/01\/04\/19\/24\/05\/95296679_p1_master1200.jpg"}