{"pid":95831588,"p":3,"uid":38015529,"title":"温蒂的私人调教","author":"DDDDECADE","r18":true,"width":4678,"height":3150,"tags":["R-18","明日方舟","Arknights","温蒂","Weedy","weedy","自慰","masturbation","ウィーディ(アークナイツ)","温蒂（明日方舟）","黒スト","黑丝袜","破れストッキング","破损的丝袜","直穿き","真空","母乳","breast milk"],"ext":"jpg","aiType":0,"uploadDate":1643364311000,"urls":{"regular":"https:\/\/i.pixiv.re\/img-master\/img\/2022\/01\/28\/19\/05\/11\/95831588_p3_master1200.jpg"},"url":"\/img-master\/img\/2022\/01\/28\/19\/05\/11\/95831588_p3_master1200.jpg"}