{"pid":96351376,"p":0,"uid":711526,"title":"マッサージその２","author":"ダイアル(片織トケイ）","r18":true,"width":848,"height":1200,"tags":["R-18","グランブルーファンタジー","碧蓝幻想","グランブルーファンタジーヴァーサス","Granblue Fantasy Versus","ジータ(グラブル)","姬塔（碧蓝幻想）","手マン","抠抠","中出し","中出","淫紋","淫纹","調教","调教","ぱんつ","胖次"],"ext":"jpg","aiType":0,"uploadDate":1645197018000,"urls":{"regular":"https:\/\/i.pixiv.re\/img-master\/img\/2022\/02\/19\/00\/10\/18\/96351376_p0_master1200.jpg"},"url":"\/img-master\/img\/2022\/02\/19\/00\/10\/18\/96351376_p0_master1200.jpg"}