{"pid":97231717,"p":1,"uid":1436637,"title":"砂狼シロコ","author":"Mujin","r18":true,"width":667,"height":1000,"tags":["R-18","ブルーアーカイブ","碧蓝档案","砂狼シロコ","Sunaookami Shiroko","シロコ(ブルーアーカイブ)","Shiroko (Blue Archive)","シロコ","オナニー","自慰","魅惑の谷間","魅惑的乳沟","揉みしだきたい乳","诱人把玩的乳房","ぱんつ","胖次"],"ext":"jpg","aiType":1,"uploadDate":1648428410000,"urls":{"regular":"https:\/\/i.pixiv.re\/img-master\/img\/2022\/03\/28\/09\/46\/50\/97231717_p1_master1200.jpg"},"url":"\/img-master\/img\/2022\/03\/28\/09\/46\/50\/97231717_p1_master1200.jpg"}