{"pid":97485772,"p":0,"uid":446045,"title":"凝光刻晴睡衣版","author":"Kacyu | 卡丘","r18":true,"width":1772,"height":2300,"tags":["R-18","原神","Genshin Impact","凝光","Ningguang","刻晴","Keqing","裸足","赤脚","美脚","美腿","陰毛","阴毛","足裏","脚底","ギリシャ型","Greek foot","へそピアス","navel piercing"],"ext":"jpg","aiType":0,"uploadDate":1649400370000,"urls":{"regular":"https:\/\/i.pixiv.re\/img-master\/img\/2022\/04\/08\/15\/46\/10\/97485772_p0_master1200.jpg"},"url":"\/img-master\/img\/2022\/04\/08\/15\/46\/10\/97485772_p0_master1200.jpg"}