{"pid":97799834,"p":1,"uid":695970,"title":"神里綾華 3 Kamisato Ayaka","author":"Megi.Nalter","r18":true,"width":3000,"height":1904,"tags":["R-18","原神","Genshin Impact","GenshinImpact","神里綾華","Ayaka Kamisato","kamisatoayaka","おっぱい","欧派","おへそ","肚脐","極上の女体","极上女体","揉みしだきたい乳","诱人把玩的乳房","さらし","缠胸布"],"ext":"jpg","aiType":0,"uploadDate":1650623510000,"urls":{"regular":"https:\/\/i.pixiv.re\/img-master\/img\/2022\/04\/22\/19\/31\/50\/97799834_p1_master1200.jpg"},"url":"\/img-master\/img\/2022\/04\/22\/19\/31\/50\/97799834_p1_master1200.jpg"}