{"pid":97963181,"p":0,"uid":216414,"title":"スク水アズサずらしっぱい","author":"ロクエさん","r18":true,"width":3000,"height":4000,"tags":["R-18","ブルーアーカイブ","碧蓝档案","白洲アズサ","Shirasu Azusa","こね回したい乳首","nipples I want to play with","乳出し","exposed breasts","クチュっと吸いたい乳首","揉みしだきたい乳","诱人把玩的乳房"],"ext":"jpg","aiType":0,"uploadDate":1651223717000,"urls":{"regular":"https:\/\/i.pixiv.re\/img-master\/img\/2022\/04\/29\/18\/15\/17\/97963181_p0_master1200.jpg"},"url":"\/img-master\/img\/2022\/04\/29\/18\/15\/17\/97963181_p0_master1200.jpg"}