{"pid":98244369,"p":0,"uid":33761760,"title":"【少女前线】FAL×Ots14","author":"RoundsChen","r18":true,"width":5542,"height":3000,"tags":["R-18","OTs-14(ドールズフロントライン)","OTs-14（少女前线）","FAL(ドールズフロントライン)","FAL（少女前线）","花嫁","新娘","骑乘位","少女前線","少女前线","巨乳","large breasts","ドールズフロントライン","白丝","White silk pantyhose","裸足","赤脚"],"ext":"jpg","aiType":0,"uploadDate":1652144738000,"urls":{"regular":"https:\/\/i.pixiv.re\/img-master\/img\/2022\/05\/10\/10\/05\/38\/98244369_p0_master1200.jpg"},"url":"\/img-master\/img\/2022\/05\/10\/10\/05\/38\/98244369_p0_master1200.jpg"}