{"pid":98767199,"p":2,"uid":5235833,"title":"Komi Beach","author":"SydusArts","r18":true,"width":720,"height":1019,"tags":["R-18","古見硝子","古见硝子","古見さんはコミュ症で","KomiCantCommunicate","おへそ","肚脐","腹","belly","おっぱい","欧派","揉みしだきたい乳","诱人把玩的乳房","古見さんは、コミュ症です。","古见同学有交流障碍症","水着","泳装"],"ext":"jpg","aiType":0,"uploadDate":1654100651000,"urls":{"regular":"https:\/\/i.pixiv.re\/img-master\/img\/2022\/06\/02\/01\/24\/11\/98767199_p2_master1200.jpg"},"url":"\/img-master\/img\/2022\/06\/02\/01\/24\/11\/98767199_p2_master1200.jpg"}