{"pid":99037146,"p":0,"uid":219917,"title":"ル・マランちゃんを秘書艦にしてお秘め事する、、、♥","author":"由訃","r18":true,"width":2023,"height":2537,"tags":["R-18","アズールレーン","碧蓝航线","アズレン","ル・マラン(アズールレーン)","恶毒（碧蓝航线）","ロリ","萝莉","昼寝好きのラピヌ","懒懒的白兔","尻コキ","臀交","ぶっかけ","射满脸","破れタイツ","破损的丝袜"],"ext":"jpg","aiType":0,"uploadDate":1655148627000,"urls":{"regular":"https:\/\/i.pixiv.re\/img-master\/img\/2022\/06\/14\/04\/30\/27\/99037146_p0_master1200.jpg"},"url":"\/img-master\/img\/2022\/06\/14\/04\/30\/27\/99037146_p0_master1200.jpg"}