{"pid":99194336,"p":0,"uid":12672233,"title":"一之瀬アスナ バニーガール","author":"赤霄","r18":true,"width":2220,"height":3106,"tags":["R-18","おっぱい","欧派","爆乳","huge breasts","極上の乳","极上乳房","魅惑の谷間","魅惑的乳沟","陰毛","阴毛","一之瀬アスナ","Asuna Ichinose","ブルーアーカイブ","碧蓝档案","バニーガール","兔女郎"],"ext":"png","aiType":0,"uploadDate":1655741429000,"urls":{"regular":"https:\/\/i.pixiv.re\/img-master\/img\/2022\/06\/21\/01\/10\/29\/99194336_p0_master1200.jpg"},"url":"\/img-master\/img\/2022\/06\/21\/01\/10\/29\/99194336_p0_master1200.jpg"}