{"pid":99318305,"p":0,"uid":10125263,"title":"風野 灯織","author":"。","r18":true,"width":1289,"height":912,"tags":["R-18","アイドルマスターシャイニーカラーズ","偶像大师 闪耀色彩","風野灯織","Hiori Kazano","アナル","肛门","顔を埋めたい股間","想把脸埋进这两腿之间","尻神様","尻神样","舐め回したい穴","想舔到不行的穴","水着","泳装","舐めたいへそ"],"ext":"jpg","aiType":0,"uploadDate":1656234964000,"urls":{"regular":"https:\/\/i.pixiv.re\/img-master\/img\/2022\/06\/26\/18\/16\/04\/99318305_p0_master1200.jpg"},"url":"\/img-master\/img\/2022\/06\/26\/18\/16\/04\/99318305_p0_master1200.jpg"}