{"pid":99315458,"p":2,"uid":885843,"title":"千利休ちゃん","author":"skeb募集中","r18":true,"width":1115,"height":833,"tags":["R-18","戦国武将姫MURAMASA","Sengoku Bushouki Muramasa","千利休","Sen no Rikyu","正常位","正常体位","ちっぱい","贫乳","挿入","penetration","パンツ","内裤","スジ","肌肉","ぱんつ","胖次"],"ext":"jpg","aiType":0,"uploadDate":1656226801000,"urls":{"regular":"https:\/\/i.pixiv.re\/img-master\/img\/2022\/06\/26\/16\/00\/01\/99315458_p2_master1200.jpg"},"url":"\/img-master\/img\/2022\/06\/26\/16\/00\/01\/99315458_p2_master1200.jpg"}