{"pid":99385333,"p":7,"uid":16141630,"title":"Dorothy","author":"SonalBiert","r18":true,"width":2265,"height":3941,"tags":["R-18","アークナイツ","明日方舟","Arknights","arknights","Dorothy","母乳","breast milk","手マン","抠抠","多萝西","ドロシー(アークナイツ)","多萝西（明日方舟）","腋見せのポーズ","Showing off armpits"],"ext":"jpg","aiType":1,"uploadDate":1656502190000,"urls":{"regular":"https:\/\/i.pixiv.re\/img-master\/img\/2022\/06\/29\/20\/29\/50\/99385333_p7_master1200.jpg"},"url":"\/img-master\/img\/2022\/06\/29\/20\/29\/50\/99385333_p7_master1200.jpg"}